[{"name":"Gold Gram 18k","price":"14,259,661"},{"name":"Gold Mithqal","price":"61,770,000"},{"name":"Gold Ounce","price":"4,509.34"},{"name":"US Dollar","price":"134100"},{"name":"Euro","price":"157800"},{"name":"British Pound","price":"180750"},{"name":"Swiss Franc","price":"169600"},{"name":"Canadian Dollar","price":"97750"},{"name":"Australian Dollar","price":"89700"},{"name":"Swedish Krona","price":"14600"},{"name":"Norwegian Krone","price":"13300"},{"name":"Russian Ruble","price":"1720"},{"name":"Thai Baht","price":"4305"},{"name":"Singapore Dollar","price":"104300"},{"name":"Hong Kong Dollar","price":"17250"},{"name":"Azerbaijani Manat","price":"78850"},{"name":"10Armenian Dram","price":"3515"},{"name":"Danish Krone","price":"21150"},{"name":"UAE Dirham","price":"36900"},{"name":"10Japanese Yen","price":"8580"},{"name":"Turkish Lira","price":"3130"},{"name":"Chinese Yuan","price":"19050"},{"name":"KSA Riyal","price":"35750"},{"name":"Indian Rupee","price":"1495"},{"name":"Ringgit","price":"33000"},{"name":"Afghan Afghani","price":"2030"},{"name":"Kuwaiti Dinar","price":"436550"},{"name":"100Iraqi Dinar","price":"10250"},{"name":"Bahraini Dinar","price":"355650"},{"name":"Omani Rial","price":"348750"},{"name":"Qatari Riyal","price":"36700"},{"name":"Azadi","price":"141,500,000"},{"name":"Emami","price":"147,900,000"},{"name":"½Azadi","price":"80,500,000"},{"name":"¼Azadi","price":"46,600,000"},{"name":"Gerami","price":"20,500,000"},{"name":"Bitcoin","price":87427.25865933608,"percent_change_24h":-1.12875319},{"name":"Ethereum","price":2969.84117287814,"percent_change_24h":-1.13002941},{"name":"Tether USDt","price":0.999403089738564,"percent_change_24h":-0.00280287},{"name":"BNB","price":844.1346613588797,"percent_change_24h":-1.53216276},{"name":"XRP","price":1.8759245569161336,"percent_change_24h":-1.37579338},{"name":"USDC","price":0.9997381426873984,"percent_change_24h":-0.00257434},{"name":"Solana","price":124.05080156215034,"percent_change_24h":-1.25257079},{"name":"TRON","price":0.2834084398753687,"percent_change_24h":-0.30980653},{"name":"Dogecoin","price":0.1294043059970496,"percent_change_24h":-2.22812603},{"name":"Cardano","price":0.3633235961569634,"percent_change_24h":-1.96574863},{"name":"Bitcoin Cash","price":573.2111710442396,"percent_change_24h":-2.75482558},{"name":"Chainlink","price":12.400539304939686,"percent_change_24h":-1.37743419},{"name":"Monero","price":448.8754482812856,"percent_change_24h":-2.83492517},{"name":"Hyperliquid","price":23.94965956365035,"percent_change_24h":-3.68210884},{"name":"UNUS SED LEO","price":7.881225208261244,"percent_change_24h":-4.73093154},{"name":"Stellar","price":0.2172877553095317,"percent_change_24h":-1.30770373},{"name":"Zcash","price":415.81011636217033,"percent_change_24h":-3.34305364},{"name":"Ethena USDe","price":0.9987263944033248,"percent_change_24h":0.01380014},{"name":"Litecoin","price":76.86697623736238,"percent_change_24h":-0.12276864},{"name":"Sui","price":1.4362697998677143,"percent_change_24h":-1.48042939},{"name":"Dai","price":0.9996654840453012,"percent_change_24h":0.00779189},{"name":"Avalanche","price":12.1852163245823,"percent_change_24h":-1.65082028},{"name":"Hedera","price":0.1105979497624317,"percent_change_24h":-3.02312472},{"name":"Shiba Inu","price":7.119613115622669e-06,"percent_change_24h":-1.15565607},{"name":"PayPal USD","price":0.9994322111140876,"percent_change_24h":0.00053841},{"name":"Uniswap","price":5.8257464356123,"percent_change_24h":-2.92159819},{"name":"Cronos","price":0.0947004552255741,"percent_change_24h":-1.02827567},{"name":"Toncoin","price":1.4842651651538583,"percent_change_24h":1.34879322},{"name":"World Liberty Financial","price":0.131580123360797,"percent_change_24h":-2.01958693},{"name":"Mantle","price":1.0591286502285564,"percent_change_24h":-4.23331872},{"name":"Canton","price":0.093875762920742,"percent_change_24h":5.42802627},{"name":"Polkadot","price":1.7644920468116323,"percent_change_24h":-0.81242877},{"name":"World Liberty Financial USD","price":0.9990439231359126,"percent_change_24h":0.01348751},{"name":"Bitget Token","price":3.4590154440753653,"percent_change_24h":-1.02080826},{"name":"OKB","price":110.1152487182944,"percent_change_24h":-0.63233838},{"name":"Aave","price":150.63706856623944,"percent_change_24h":0.29604626},{"name":"Bittensor","price":214.3955038753356,"percent_change_24h":-3.5592253},{"name":"NEAR Protocol","price":1.4895943829829104,"percent_change_24h":-0.78228335},{"name":"Ethereum Classic","price":12.072941281442878,"percent_change_24h":-1.45880526},{"name":"Aster","price":0.6881521901723868,"percent_change_24h":-1.75464385},{"name":"Tether Gold","price":4508.741855802557,"percent_change_24h":1.08260947},{"name":"MemeCore","price":1.361139702196238,"percent_change_24h":0.10816634},{"name":"Pi","price":0.2029514286017393,"percent_change_24h":-0.39405999},{"name":"Pepe","price":3.940950449108051e-06,"percent_change_24h":-1.56370361},{"name":"Internet Computer","price":3.0246313195213226,"percent_change_24h":-0.34742507},{"name":"PAX Gold","price":4526.902210324189,"percent_change_24h":1.10981523},{"name":"Ethena","price":0.2001022565754998,"percent_change_24h":-3.07356601},{"name":"Global Dollar","price":0.99954564435674,"percent_change_24h":-0.0064144},{"name":"Sky","price":0.0648021564351011,"percent_change_24h":-3.07304311},{"name":"KuCoin Token","price":10.84518865033409,"percent_change_24h":0.03397841},{"name":"Ripple USD","price":0.9996650293418432,"percent_change_24h":0.0154681},{"name":"Midnight","price":0.0787257875559838,"percent_change_24h":-23.86116169},{"name":"Worldcoin","price":0.4933833449635832,"percent_change_24h":-2.06016813},{"name":"Kaspa","price":0.0452153310943457,"percent_change_24h":-3.13044485},{"name":"Ondo","price":0.386763428565437,"percent_change_24h":-1.50685429},{"name":"Aptos","price":1.6088685440475703,"percent_change_24h":-0.68317378},{"name":"Polygon (prev. MATIC)","price":0.1067731457200099,"percent_change_24h":-1.02965877},{"name":"Arbitrum","price":0.1903192063848236,"percent_change_24h":1.61421035},{"name":"Algorand","price":0.1134897719410672,"percent_change_24h":1.57589817},{"name":"OFFICIAL TRUMP","price":4.955662442766378,"percent_change_24h":-0.3465941},{"name":"Filecoin","price":1.3119529582338758,"percent_change_24h":1.11383222},{"name":"Cosmos","price":1.968454321651245,"percent_change_24h":1.01004128},{"name":"Flare","price":0.0113041296269598,"percent_change_24h":-3.47826412},{"name":"Quant","price":75.34994909570143,"percent_change_24h":0.55223324},{"name":"VeChain","price":0.0105164685092566,"percent_change_24h":-0.77920787},{"name":"XDC Network","price":0.0485532986031157,"percent_change_24h":1.90833002},{"name":"USDD","price":0.9993319858823768,"percent_change_24h":-0.01319027},{"name":"GateToken","price":10.208402237072963,"percent_change_24h":-1.42572619},{"name":"MYX Finance","price":3.229637972830849,"percent_change_24h":-2.4633065},{"name":"Sei","price":0.1099721070602831,"percent_change_24h":-2.70288319},{"name":"Bonk","price":7.980759245993312e-06,"percent_change_24h":-1.59450847},{"name":"Render","price":1.2753588435769476,"percent_change_24h":-0.69569468},{"name":"Pump.fun","price":0.001735675854959,"percent_change_24h":-9.10280724},{"name":"PancakeSwap","price":1.8011696738683294,"percent_change_24h":-2.59038807},{"name":"Nexo","price":0.9341684531176208,"percent_change_24h":0.91178657},{"name":"Jupiter","price":0.1904300088807949,"percent_change_24h":-0.6800963},{"name":"Pudgy Penguins","price":0.0088091326180398,"percent_change_24h":-3.33897397},{"name":"Curve DAO Token","price":0.3740404666921336,"percent_change_24h":-1.12504113},{"name":"Optimism","price":0.2704381206562703,"percent_change_24h":-0.31616538},{"name":"First Digital USD","price":0.9989141915084744,"percent_change_24h":0.00341728},{"name":"Story","price":1.4784262862879216,"percent_change_24h":-2.73992872},{"name":"TrueUSD","price":0.9987614709007676,"percent_change_24h":0.3128235},{"name":"Artificial Superintelligence Alliance","price":0.2098484821210595,"percent_change_24h":1.4662812},{"name":"Lido DAO","price":0.5363133652069645,"percent_change_24h":-1.78318463},{"name":"Tezos","price":0.4433547904386409,"percent_change_24h":0.183906},{"name":"Dash","price":37.71094643883549,"percent_change_24h":-1.53565673},{"name":"ether.fi","price":0.7080793492538272,"percent_change_24h":-1.80377606},{"name":"pippin","price":0.4614481344857388,"percent_change_24h":26.66162704},{"name":"Virtuals Protocol","price":0.7016918926781957,"percent_change_24h":-0.68389244},{"name":"Injective","price":4.597575201087741,"percent_change_24h":-1.14596339},{"name":"Merlin Chain","price":0.4192247992841751,"percent_change_24h":-0.04778285},{"name":"Immutable","price":0.2278787698904487,"percent_change_24h":0.6108119},{"name":"Morpho","price":1.1830959035198036,"percent_change_24h":-1.79910206},{"name":"Stacks","price":0.2443145839594366,"percent_change_24h":-1.30929834},{"name":"SPX6900","price":0.4751651703688122,"percent_change_24h":-0.61200297},{"name":"AB","price":0.0047333242874183,"percent_change_24h":-4.97855346},{"name":"Aerodrome Finance","price":0.4827262387128797,"percent_change_24h":-2.73757382},{"name":"Starknet","price":0.0798966552900981,"percent_change_24h":1.54379843},{"name":"JUST","price":0.0399470982874183,"percent_change_24h":0.13064877},{"name":"Audiera","price":2.403784130278222,"percent_change_24h":-36.62760242}]