[{"name":"Gold Gram 18k","price":"14,322,683"},{"name":"Gold Mithqal","price":"62,043,000"},{"name":"Gold Ounce","price":"4,479.53"},{"name":"US Dollar","price":"134650"},{"name":"Euro","price":"158550"},{"name":"British Pound","price":"181700"},{"name":"Swiss Franc","price":"170750"},{"name":"Canadian Dollar","price":"98450"},{"name":"Australian Dollar","price":"90300"},{"name":"Swedish Krona","price":"14700"},{"name":"Norwegian Krone","price":"13450"},{"name":"Russian Ruble","price":"1705"},{"name":"Thai Baht","price":"4335"},{"name":"Singapore Dollar","price":"104850"},{"name":"Hong Kong Dollar","price":"17300"},{"name":"Azerbaijani Manat","price":"78900"},{"name":"10Armenian Dram","price":"3530"},{"name":"Danish Krone","price":"21200"},{"name":"UAE Dirham","price":"36850"},{"name":"10Japanese Yen","price":"8630"},{"name":"Turkish Lira","price":"3140"},{"name":"Chinese Yuan","price":"19150"},{"name":"KSA Riyal","price":"35900"},{"name":"Indian Rupee","price":"1500"},{"name":"Ringgit","price":"33300"},{"name":"Afghan Afghani","price":"2030"},{"name":"Kuwaiti Dinar","price":"438350"},{"name":"100Iraqi Dinar","price":"10300"},{"name":"Bahraini Dinar","price":"356950"},{"name":"Omani Rial","price":"350200"},{"name":"Qatari Riyal","price":"36950"},{"name":"Azadi","price":"143,800,000"},{"name":"Emami","price":"151,000,000"},{"name":"½Azadi","price":"82,000,000"},{"name":"¼Azadi","price":"48,000,000"},{"name":"Gerami","price":"20,800,000"},{"name":"Bitcoin","price":88068.46169002661,"percent_change_24h":0.64063024},{"name":"Ethereum","price":2953.473378996895,"percent_change_24h":0.30298556},{"name":"Tether USDt","price":0.999398578502713,"percent_change_24h":0.00310697},{"name":"BNB","price":840.628003956791,"percent_change_24h":-0.71969067},{"name":"XRP","price":1.8711052461208544,"percent_change_24h":0.59698971},{"name":"USDC","price":0.99981695111988,"percent_change_24h":-0.01431441},{"name":"Solana","price":123.34641071463628,"percent_change_24h":0.53467161},{"name":"TRON","price":0.278711051651396,"percent_change_24h":-0.8721686},{"name":"Dogecoin","price":0.1270205703512036,"percent_change_24h":-0.74957639},{"name":"Cardano","price":0.3588922306346899,"percent_change_24h":0.84444807},{"name":"Bitcoin Cash","price":595.8650218504946,"percent_change_24h":5.48384747},{"name":"Chainlink","price":12.356815136720762,"percent_change_24h":0.98023725},{"name":"Hyperliquid","price":24.93265731231076,"percent_change_24h":1.52840994},{"name":"Monero","price":437.3832933021248,"percent_change_24h":1.93320491},{"name":"UNUS SED LEO","price":8.150923126956402,"percent_change_24h":0.89619252},{"name":"Zcash","price":440.30071144280737,"percent_change_24h":-0.6154989},{"name":"Stellar","price":0.2140456483013708,"percent_change_24h":0.90302165},{"name":"Ethena USDe","price":0.9986222604622184,"percent_change_24h":-0.00633548},{"name":"Litecoin","price":77.25296101765797,"percent_change_24h":2.07165572},{"name":"Dai","price":0.9996926699097056,"percent_change_24h":0.0053695},{"name":"Avalanche","price":12.44519827304865,"percent_change_24h":3.42484926},{"name":"Sui","price":1.4086945043872998,"percent_change_24h":-0.47275634},{"name":"Hedera","price":0.1120920101923029,"percent_change_24h":2.68604222},{"name":"Shiba Inu","price":7.230473180671767e-06,"percent_change_24h":1.05038628},{"name":"Toncoin","price":1.5232144168610249,"percent_change_24h":1.86188545},{"name":"Uniswap","price":5.923378534973075,"percent_change_24h":2.52172423},{"name":"PayPal USD","price":0.9995950704392688,"percent_change_24h":0.00031742},{"name":"World Liberty Financial","price":0.1390267126710696,"percent_change_24h":5.58452391},{"name":"Cronos","price":0.0936875805477624,"percent_change_24h":1.0767602},{"name":"Canton","price":0.098652074339205,"percent_change_24h":-0.30873749},{"name":"Mantle","price":1.046100439656108,"percent_change_24h":0.80300825},{"name":"World Liberty Financial USD","price":1.0011077523313137,"percent_change_24h":0.1044169},{"name":"Polkadot","price":1.732398868207618,"percent_change_24h":0.27127868},{"name":"Bitget Token","price":3.46205095158457,"percent_change_24h":0.45259374},{"name":"Bittensor","price":225.60662917086265,"percent_change_24h":3.41546911},{"name":"Aave","price":152.88341615491814,"percent_change_24h":3.23511375},{"name":"OKB","price":108.76502618057292,"percent_change_24h":0.25575328},{"name":"NEAR Protocol","price":1.4999004217168876,"percent_change_24h":2.92199435},{"name":"Ethereum Classic","price":11.919559806313291,"percent_change_24h":-0.43639908},{"name":"Aster","price":0.6907550204119385,"percent_change_24h":-0.42202207},{"name":"Pi","price":0.2058325150537379,"percent_change_24h":0.40020485},{"name":"MemeCore","price":1.369283915236008,"percent_change_24h":-0.43967239},{"name":"Tether Gold","price":4490.664767731838,"percent_change_24h":0.15533037},{"name":"Pepe","price":4.008831520463313e-06,"percent_change_24h":1.756508},{"name":"Internet Computer","price":3.066661527243924,"percent_change_24h":3.14761619},{"name":"PAX Gold","price":4505.9458234259855,"percent_change_24h":0.23411058},{"name":"Sky","price":0.0688877434320289,"percent_change_24h":1.63456799},{"name":"Ethena","price":0.2046666120865803,"percent_change_24h":2.35313654},{"name":"Global Dollar","price":0.9996214152072342,"percent_change_24h":-0.01621663},{"name":"KuCoin Token","price":10.859343031214657,"percent_change_24h":0.2912845},{"name":"Midnight","price":0.0814526249821974,"percent_change_24h":2.4375888},{"name":"Ripple USD","price":0.9996645220766298,"percent_change_24h":-0.00370388},{"name":"Worldcoin","price":0.5008023896842951,"percent_change_24h":3.32491848},{"name":"Aptos","price":1.6425916672635077,"percent_change_24h":1.76148044},{"name":"Ondo","price":0.3828821347418867,"percent_change_24h":1.71906106},{"name":"Kaspa","price":0.0446718899808957,"percent_change_24h":1.32050081},{"name":"Polygon (prev. MATIC)","price":0.1054889033957713,"percent_change_24h":-0.07189826},{"name":"Arbitrum","price":0.190831024681194,"percent_change_24h":1.83297653},{"name":"Algorand","price":0.118104425947026,"percent_change_24h":5.55242254},{"name":"OFFICIAL TRUMP","price":4.948508318055793,"percent_change_24h":0.93831884},{"name":"Cosmos","price":2.005312112410285,"percent_change_24h":2.87560222},{"name":"Filecoin","price":1.2728810035104006,"percent_change_24h":-0.22236538},{"name":"Flare","price":0.0114806070926527,"percent_change_24h":1.59640407},{"name":"VeChain","price":0.0106644792133154,"percent_change_24h":1.78262563},{"name":"XDC Network","price":0.0485938974320667,"percent_change_24h":-1.82818422},{"name":"Quant","price":73.96409889376102,"percent_change_24h":0.42289663},{"name":"MYX Finance","price":3.3150184763369097,"percent_change_24h":3.25668072},{"name":"USDD","price":0.9993765960446552,"percent_change_24h":-0.02015601},{"name":"GateToken","price":10.187503697120652,"percent_change_24h":-0.40651252},{"name":"Sei","price":0.1107853991603962,"percent_change_24h":1.72902541},{"name":"Render","price":1.2872763685324216,"percent_change_24h":2.88335345},{"name":"Bonk","price":7.899271405099799e-06,"percent_change_24h":1.04425092},{"name":"Pump.fun","price":0.0017915635999675,"percent_change_24h":2.05208546},{"name":"Jupiter","price":0.1994901658726471,"percent_change_24h":2.99590431},{"name":"PancakeSwap","price":1.8339320775823893,"percent_change_24h":0.17080973},{"name":"Nexo","price":0.9124942291216004,"percent_change_24h":-0.04838449},{"name":"Pudgy Penguins","price":0.0091490989696251,"percent_change_24h":-0.36096125},{"name":"Curve DAO Token","price":0.3995476592124022,"percent_change_24h":6.06697196},{"name":"First Digital USD","price":0.9988041992460264,"percent_change_24h":-0.00439255},{"name":"Optimism","price":0.2614222233671058,"percent_change_24h":-0.60038155},{"name":"Story","price":1.4934337185935431,"percent_change_24h":0.05425634},{"name":"pippin","price":0.5022142319050426,"percent_change_24h":3.20489411},{"name":"Merlin Chain","price":0.4560657254532413,"percent_change_24h":6.2203378},{"name":"TrueUSD","price":0.9979327195047571,"percent_change_24h":-0.04982997},{"name":"Dash","price":39.30971644398127,"percent_change_24h":4.44007633},{"name":"Tezos","price":0.4557478330852684,"percent_change_24h":4.90780781},{"name":"Artificial Superintelligence Alliance","price":0.2096719490254428,"percent_change_24h":0.85906295},{"name":"Lido DAO","price":0.5623850497070974,"percent_change_24h":6.01825801},{"name":"Immutable","price":0.2374570556734566,"percent_change_24h":1.81924914},{"name":"Injective","price":4.632605925086598,"percent_change_24h":2.70897448},{"name":"Stacks","price":0.2534878473017071,"percent_change_24h":3.2685979},{"name":"SPX6900","price":0.4921071223940263,"percent_change_24h":4.01962041},{"name":"ether.fi","price":0.700116827163366,"percent_change_24h":0.23844081},{"name":"Virtuals Protocol","price":0.6908959842984478,"percent_change_24h":0.12433925},{"name":"Aerodrome Finance","price":0.4871972555424823,"percent_change_24h":1.54941581},{"name":"AB","price":0.004684928654652,"percent_change_24h":-0.65450124},{"name":"Morpho","price":1.1545492632166408,"percent_change_24h":0.55270971},{"name":"DoubleZero","price":0.1245195363789003,"percent_change_24h":10.03047015},{"name":"Starknet","price":0.0806846191037195,"percent_change_24h":0.64717658},{"name":"Maple Finance","price":0.3456524946522689,"percent_change_24h":11.77077297}]